{"code":"import turtle\n\nwn = turtle.Screen()\nwn.bgcolor(\"green\")","type":1,"guide":[{"id":"tut1","img":"<p style='margin:0cm;font-size:16px;font-family:\"Calibri\",sans-serif;'><span style=\"color: rgb(239, 239, 239), background-color: rgb(0, 0, 0), font-size: 22px;\">In the next set of lessons, we will be working on creating a simple game using everything we have learned so far</span></p>\n","code":"import turtle","audio":""},{"id":"tut2","img":"<p style='margin:0cm;font-size:16px;font-family:\"Calibri\",sans-serif;'><span style=\"color: rgb(239, 239, 239), background-color: rgb(0, 0, 0), font-size: 22px;\">Let&rsquo;s begin by creating a screen, and setting the screen colour like green for our game</span></p>\n","code":"import turtle\n\nwn = turtle.Screen()\nwn.bgcolor(\"green\")","audio":""}]}