{
    "lesson": "204",
    "type": 3,
    "code": "cars=('audi','benz','nexus','audi')\ncity=('New york','washington','Boston')\nprint(cars+city)",
    "user_code": "",
    "guide": {
        "English": [
            {
                "id": "tut3",
                "img": "+ operator adds two tuples",
                "code": "cars=('audi','benz','nexus','audi')\ncity=('New york','washington','Boston')\nprint(cars+",
                "audio": "Py_Eng_Lesson_204_1.mp3"
            }
        ]
    }
}